pyimpedancemodel/C.py
pyimpedancemodel/CPE.py
pyimpedancemodel/FLW.py
pyimpedancemodel/FSW.py
pyimpedancemodel/G.py
pyimpedancemodel/ImpedanceModel.py
pyimpedancemodel/ImpedanceModelElement.py
pyimpedancemodel/L.py
pyimpedancemodel/R.py
pyimpedancemodel/R_CPE.py
pyimpedancemodel/R_HN.py
pyimpedancemodel/W.py
pyimpedancemodel/__init__.py
pyimpedancemodel-1.0.dist-info/licenses/LICENSE
pyimpedancemodel-1.0.dist-info/METADATA
pyimpedancemodel-1.0.dist-info/WHEEL
pyimpedancemodel-1.0.dist-info/top_level.txt
pyimpedancemodel-1.0.dist-info/RECORD
