Metadata-Version: 2.4
Name: PyImpedanceModel
Version: 1.0
Summary: A fast, lean library for modeling and fitting equivalent circuit models for electrochemical impedance spectroscopy data.
Author-email: Robert Leonhardt <mail@robertleonhardt.de>
License: MIT License
Project-URL: Homepage, https://github.com/robertleonhardt/PyImpedanceModel
Project-URL: Source, https://github.com/robertleonhardt/PyImpedanceModel
Project-URL: Issues, https://github.com/robertleonhardt/PyImpedanceModel/issues
Requires-Python: >=3.10
License-File: LICENSE
Requires-Dist: numpy>=2.2
Requires-Dist: scipy>=1.15
Dynamic: license-file
